[{"title":"不良人3","publisher":"艾瑞爾網路股份有限公司","platform":"手機遊戲","old":{"級別":"輔12","情節":"暴力","上市日期":"未上市"},"new":{"級別":"輔12","情節":"性,暴力","上市日期":"未上市"}},{"title":"酷游3缺1","publisher":"樂博勝網路科技有限公司","platform":"手機遊戲","old":{"級別":"輔15","情節":"棋奕,牌類及益智娛樂","上市日期":"2022/12/02"},"new":{"級別":"輔15","情節":"棋奕,牌類及益智娛樂","上市日期":"未上市"}},{"title":"仙宗大掌門","publisher":"輝夜遊戲有限公司","platform":"手機遊戲","old":{"級別":"輔12","情節":"暴力","上市日期":"未上市"},"new":{"級別":"輔12","情節":"暴力","上市日期":"2022/12/16"}},{"title":"Rocket Lift","publisher":"Webnetic s. r. o.","platform":"PS4","old":{"級別":"普","情節":"未涉及任何情節","上市日期":"未上市"},"new":{"級別":"普","情節":"未涉及任何情節","上市日期":"2022/12/15"}},{"title":"Rocket Lift","publisher":"Webnetic s. r. o.","platform":"PS5","old":{"級別":"普","情節":"未涉及任何情節","上市日期":"未上市"},"new":{"級別":"普","情節":"未涉及任何情節","上市日期":"2022/12/15"}},{"title":"馴龍傳說","publisher":"易亨數位行銷有限公司","platform":"手機遊戲","old":{"級別":"輔12","情節":"性,暴力","上市日期":"未上市"},"new":{"級別":"輔12","情節":"性,暴力","上市日期":"2022/12/15"}},{"title":"盧希達：起源","publisher":"易亨數位行銷有限公司","platform":"手機遊戲","old":{"級別":"輔12","情節":"性,暴力","上市日期":"未上市"},"new":{"級別":"輔12","情節":"性,暴力","上市日期":"2022/12/15"}},{"title":"NAIAD","publisher":"HIWARP SL","platform":"PS4","old":{"級別":"普","情節":"未涉及任何情節","上市日期":"未上市"},"new":{"級別":"普","情節":"未涉及任何情節","上市日期":"2022/12/15"}},{"title":"NAIAD","publisher":"HIWARP SL","platform":"PS5","old":{"級別":"普","情節":"未涉及任何情節","上市日期":"未上市"},"new":{"級別":"普","情節":"未涉及任何情節","上市日期":"2022/12/15"}},{"title":"NAIAD","publisher":"HIWARP SL","platform":"Xbox","old":{"級別":"普","情節":"未涉及任何情節","上市日期":"未上市"},"new":{"級別":"普","情節":"未涉及任何情節","上市日期":"2022/12/15"}},{"title":"NAIAD","publisher":"HIWARP SL","platform":"Switch","old":{"級別":"普","情節":"未涉及任何情節","上市日期":"未上市"},"new":{"級別":"普","情節":"未涉及任何情節","上市日期":"2022/12/15"}},{"title":"神迹幻鏡","publisher":"艾肯娛樂股份有限公司","platform":"手機遊戲","old":{"級別":"輔15","情節":"暴力,不當言語,戀愛交友","上市日期":"未上市"},"new":{"級別":"輔15","情節":"暴力,不當言語,戀愛交友","上市日期":"2022/12/15"}},{"title":"蒼藍雷霆 GUNVOLT 3 鎖環","publisher":"傑仕登股份有限公司","platform":"PS4","old":{"級別":"輔12","情節":"性,暴力","上市日期":"未上市"},"new":{"級別":"輔12","情節":"性,暴力","上市日期":"2022/12/15"}},{"title":"律動軌跡","publisher":"河流遊戲股份有限公司","platform":"手機遊戲","old":{"級別":"輔12","情節":"性","上市日期":"未上市"},"new":{"級別":"輔12","情節":"性","上市日期":"2022/12/15"}},{"title":"鋼之鍊金術師 M","publisher":"新加坡商競舞電競有限公司臺灣分公司","platform":"手機遊戲","old":{"級別":"輔15","情節":"性,暴力,菸酒","上市日期":"未上市"},"new":{"級別":"輔15","情節":"性,暴力,菸酒","上市日期":"2022/12/15"}},{"title":"巫師 3：狂獵","publisher":"Epicsoft (Hong Kong) Limited","platform":"PS5","old":{"級別":"限","情節":"性,暴力,恐怖","上市日期":"未上市"},"new":{"級別":"限","情節":"性,暴力,恐怖","上市日期":"2022/12/14"}},{"title":"巫師 3：狂獵","publisher":"Epicsoft (Hong Kong) Limited","platform":"Xbox Series X|S","old":{"級別":"限","情節":"性,暴力,恐怖","上市日期":"未上市"},"new":{"級別":"限","情節":"性,暴力,恐怖","上市日期":"2022/12/14"}},{"title":"Raptor Boyfriend: A High School Romance","publisher":"Eastasiasoft Limited","platform":"PS4","old":{"級別":"限","情節":"性,暴力,菸酒,毒品,不當言語","上市日期":"未上市"},"new":{"級別":"限","情節":"性,暴力,菸酒,毒品,不當言語","上市日期":"2022/12/14"}},{"title":"Raptor Boyfriend: A High School Romance","publisher":"Eastasiasoft Limited","platform":"PS5","old":{"級別":"限","情節":"性,暴力,菸酒,毒品,不當言語","上市日期":"未上市"},"new":{"級別":"限","情節":"性,暴力,菸酒,毒品,不當言語","上市日期":"2022/12/14"}},{"title":"Broken Pipe","publisher":"Volkov Konstantin Sergeevich","platform":"PS4","old":{"級別":"護","情節":"暴力","上市日期":"未上市"},"new":{"級別":"護","情節":"暴力","上市日期":"2022/12/12"}},{"title":"Bunny Memory","publisher":"Volkov Konstantin Sergeevich","platform":"PS4","old":{"級別":"護","情節":"暴力","上市日期":"未上市"},"new":{"級別":"護","情節":"暴力","上市日期":"2022/12/11"}},{"title":"發明工坊：翠斯堤亞的遺產","publisher":"SOFT SOURCE PTE LTD","platform":"Switch","old":{"級別":"輔15","情節":"性","上市日期":"2022/12/07"},"new":{"級別":"輔15","情節":"性,菸酒","上市日期":"2022/12/07"}},{"title":"發明工坊：發明工坊兩款同捆包","publisher":"SOFT SOURCE PTE LTD","platform":"Switch","old":{"級別":"輔15","情節":"性","上市日期":"2022/12/07"},"new":{"級別":"輔15","情節":"性,菸酒","上市日期":"2022/12/07"}},{"title":"奇珍物語","publisher":"耀點國際有限公司","platform":"手機遊戲","old":{"級別":"護","情節":"暴力","上市日期":"2022/08/15"},"new":{"級別":"輔12","情節":"暴力","上市日期":"2022/08/15"}},{"title":"ALICE Fiction 漂眇群像","publisher":"Wonderplanet Global Pte. Ltd.","platform":"手機遊戲","old":{"級別":"輔12","情節":"未涉及任何情節","上市日期":"2022/07/06"},"new":{"級別":"輔12","情節":"性,暴力","上市日期":"2022/07/06"}},{"title":"末日喧囂","publisher":"珩熠文化網路有限公司","platform":"手機遊戲","old":{"級別":"輔15","情節":"性,暴力","上市日期":"2021/03/29"},"new":{"級別":"輔15","情節":"性,暴力,恐怖","上市日期":"2021/03/29"}},{"title":"新希望","publisher":"珩熠文化網路有限公司","platform":"手機遊戲","old":{"級別":"輔15","情節":"性,暴力,菸酒,戀愛交友","上市日期":"2021/01/28"},"new":{"級別":"輔12","情節":"性,暴力,戀愛交友","上市日期":"2021/01/28"}},{"title":"幻書啟世錄","publisher":"恩奕互動娛樂有限公司","platform":"手機遊戲","old":{"級別":"輔15","情節":"性,暴力,恐怖","上市日期":"2021/01/07"},"new":{"級別":"輔15","情節":"性,暴力,恐怖,戀愛交友","上市日期":"2021/01/07"}},{"title":"封神異世錄","publisher":"瑞緹整合行銷有限公司","platform":"手機遊戲","old":{"級別":"護","情節":"暴力","上市日期":"2020/12/01"},"new":{"級別":"輔12","情節":"性,暴力,戀愛交友","上市日期":"2020/12/01"}},{"title":"Frane: Dragons' Odyssey","publisher":"Kotobuki Solution Co., Ltd.(KEMCO )","platform":"PS4","old":{"級別":"輔15","情節":"反社會性","上市日期":"2020/02/12"},"new":{"級別":"輔15","情節":"性,暴力,反社會性,牌類及益智娛樂","上市日期":"2020/02/12"}},{"title":"Sephirothic Stories","publisher":"Kotobuki Solution Co., Ltd.(KEMCO )","platform":"PS4","old":{"級別":"普","情節":"未涉及任何情節","上市日期":"2020/02/10"},"new":{"級別":"輔12","情節":"不當言語","上市日期":"2020/02/10"}},{"title":"Illusion of L''Phalcia","publisher":"Kotobuki Solution Co., Ltd.(KEMCO )","platform":"PS4","old":{"級別":"普","情節":"未涉及任何情節","上市日期":"2019/12/02"},"new":{"級別":"輔12","情節":"不當言語","上市日期":"2019/12/02"}},{"title":"Illusion of L''Phalcia","publisher":"Kotobuki Solution Co., Ltd.(KEMCO )","platform":"PSVITA","old":{"級別":"普","情節":"未涉及任何情節","上市日期":"2019/12/02"},"new":{"級別":"輔12","情節":"不當言語","上市日期":"2019/12/02"}}]